m5expr.py
m5expr-1.0.10.dist-info/LICENSE
m5expr-1.0.10.dist-info/METADATA
m5expr-1.0.10.dist-info/WHEEL
m5expr-1.0.10.dist-info/top_level.txt
m5expr-1.0.10.dist-info/RECORD
